{"chapter":5,"bookCode":"1corintians","size":12,"bookName":"1 Corinthians","bookNameJPN":"コリント人への手紙Ⅰ","verses":{"1":"あなたがたの間に起こった不品行について、みながうわさをしています。それは、異教徒でもしないほどの不品行で、父の妻（おそらく継母のこと）と関係を持っている人が、教会にいるそうではありませんか。","2":"それでもなお、自分たちは信仰深いとしらを切るつもりですか。どうしてそのことで嘆き悲しみ、恥じないのですか。なぜその人を教会から除名しないのですか。","3":"私はそこにはいっしょにいませんが、私もこの問題をよく考えてみました。そして、実際その場に居合わせたように、主イエス・キリストの御名によって、すでに対策を決めました。さっそく教会で集会を開きなさい。\u2015\u2015その時、主イエスの力があなたがたと共にあり、私も霊において出席します。\u2015\u2015","5":"そして、その人を罰するために、教会から追放してサタンの手に引き渡しなさい。そうするのは、主イエス・キリストが帰って来られる時に、その人のたましいが救われるようにと願うからです。","6":"あなたがたが、このようなことに目をつぶっているかと思うと、ぞっとします。たとえ一人でも、罪を犯すままに放任しておけば、やがてその影響が全員に及ぶことがわからないのですか。","7":"その人を、あなたがたの間から除きなさい。そうすれば、きよさを保てます。神の小羊であるキリストは、私たちのためにすでに殺されたのです。","8":"ですから、悪意や不正でいっぱいの生活から、完全に離れなさい。しっかりキリストにつながり、クリスチャン生活において、力強く成長しようではありませんか。悪意や不正のまじったパンではなく、誠実と真実という純粋なパンを食べようではありませんか。","9":"私は以前、あなたがたに手紙で、不品行な者たちと交際しないように書き送りました。","10":"しかしそれは、信者でない人で性的な罪を犯している者、強欲な者、どろぼう、偶像を拝む者とは口もきくな、という意味ではありません。そのような人たちから離れていようとすれば、この世から出て行かなければならないからです。","11":"私がほんとうに意図したところは、自分はクリスチャンだと公言している者で、しかも性的な罪にふける者、貪欲な者、人をだます者、偶像を拝む者、酒に酔う者、人をそしる者とはつき合うな、ということです。そのような者とは、いっしょに食事をすることもいけません。","12":"教会外の人たちをさばくことは、私たちの務めではありません。神おひとりのなさることです。しかし、教会員でありながら、このような罪を犯す者がいたら、教会として処置をとることは当然です。その悪い人を教会から除かなければなりません。"}}